LICENSE
MANIFEST.in
README.md
requirements.txt
setup.py
bin/prom2teams
bin/prom2teams_uwsgi
bin/wsgi.py
prom2teams/__init__.py
prom2teams.egg-info/PKG-INFO
prom2teams.egg-info/SOURCES.txt
prom2teams.egg-info/dependency_links.txt
prom2teams.egg-info/not-zip-safe
prom2teams.egg-info/requires.txt
prom2teams.egg-info/top_level.txt
prom2teams/app/__init__.py
prom2teams/app/api.py
prom2teams/app/configuration.py
prom2teams/app/exceptions.py
prom2teams/app/sender.py
prom2teams/app/teams_client.py
prom2teams/app/static/favicon.ico
prom2teams/app/versions/__init__.py
prom2teams/app/versions/v1/__init__.py
prom2teams/app/versions/v1/model.py
prom2teams/app/versions/v1/namespace.py
prom2teams/app/versions/v2/__init__.py
prom2teams/app/versions/v2/model.py
prom2teams/app/versions/v2/namespace.py
prom2teams/config/__init__.py
prom2teams/config/logging.yml
prom2teams/config/settings.py
prom2teams/prometheus/__init__.py
prom2teams/prometheus/message_schema.py
prom2teams/resources/templates/teams.j2
prom2teams/teams/__init__.py
prom2teams/teams/alert_mapper.py
prom2teams/teams/composer.py
prom2teams/teams/teams_alert_schema.py
prom2teams/teams/teams_alert_validation.py