Metadata-Version: 2.1
Name: prom2teams
Version: 3.2.3
Summary: Project that redirects Prometheus Alert Manager notifications to Microsoft Teams
Home-page: https://github.com/idealista/prom2teams
Author: Idealista, S.A.U
Author-email: labs@idealista.com
License: Apache license 2.0
Keywords: microsoft teams prometheus alert
Platform: UNKNOWN
Classifier: Development Status :: 5 - Production/Stable
Classifier: Topic :: Utilities
Classifier: Topic :: Communications :: Chat
Classifier: License :: OSI Approved :: Apache Software License
Classifier: Intended Audience :: Developers
Classifier: Intended Audience :: System Administrators
Classifier: Topic :: System :: Monitoring
Classifier: Programming Language :: Python
Classifier: Programming Language :: Python :: 3.6
Classifier: Programming Language :: Python :: 3.7
Classifier: Programming Language :: Python :: 3.8
License-File: LICENSE
